geotecha/CHANGELOG.txt
geotecha/LICENSE.txt
geotecha/README.rst
geotecha/__init__.py
geotecha/.libs/libepus_ext.23FPTAURLLQKHU4T6FV22APZWF2GAKAQ.gfortran-win_amd64.dll
geotecha/.libs/libext_inte.DL3KXBWHLIYNXNRSX6LTWT7XEXSLWMYR.gfortran-win_amd64.dll
geotecha/beam_on_foundation/__init__.py
geotecha/beam_on_foundation/dingetal2012.py
geotecha/beam_on_foundation/specbeam.py
geotecha/beam_on_foundation/test/__init__.py
geotecha/beam_on_foundation/test/test_dingetal2012.py
geotecha/beam_on_foundation/test/test_specbeam.py
geotecha/consolidation/__init__.py
geotecha/consolidation/cosenzaandkorosak2014.py
geotecha/consolidation/dengetal2013and2014.py
geotecha/consolidation/luetal2010.py
geotecha/consolidation/nogamiandli2003.py
geotecha/consolidation/nogamiandli2003_interactive.py
geotecha/consolidation/schiffmanandstein1970.py
geotecha/consolidation/schiffmanandstein1970_interactive.py
geotecha/consolidation/shanetal2012.py
geotecha/consolidation/smear_zones.py
geotecha/consolidation/tangandonitsuka2000.py
geotecha/consolidation/terzahi.py
geotecha/consolidation/xieandleo2004.py
geotecha/consolidation/zhuandyin2012.py
geotecha/consolidation/test/__init__.py
geotecha/consolidation/test/test_dengetal2013and2014.py
geotecha/consolidation/test/test_schiffmanandstein1970.py
geotecha/consolidation/test/test_smear_zones.py
geotecha/consolidation/test/test_tangandonitsuka2000.py
geotecha/consolidation/test/test_xieandleo2004.py
geotecha/constitutive_models/__init__.py
geotecha/constitutive_models/epus.py
geotecha/constitutive_models/epus_ext.cp36-win_amd64.pyd
geotecha/constitutive_models/epus_ext.f95
geotecha/constitutive_models/swcc.py
geotecha/constitutive_models/velocity_hydraulic_gradient.py
geotecha/constitutive_models/void_ratio_permeability.py
geotecha/constitutive_models/void_ratio_stress.py
geotecha/constitutive_models/test/EPUS_test_data_case01.csv
geotecha/constitutive_models/test/__init__.py
geotecha-0.2.2.dist-info/METADATA
geotecha-0.2.2.dist-info/RECORD
geotecha-0.2.2.dist-info/WHEEL
geotecha-0.2.2.dist-info/entry_points.txt
geotecha-0.2.2.dist-info/top_level.txt
