Metadata-Version: 2.1
Name: geotecha
Version: 0.2.2
Summary: geotecha: A software suite for geotechncial engineering
Home-page: https://github.com/rtrwalker/geotecha.git
Author: Dr Rohan Walker
Author-email: rtrwalker@gmail.com
Maintainer: Dr Rohan Walker
Maintainer-email: rtrwalker@gmail.com
License: GNU General Public License v3 or later (    )
Download-URL: https://github.com/rtrwalker/geotecha.git
Platform: Windows
Classifier: Development Status :: 4 - Beta
Classifier: License :: OSI Approved :: GNU Lesser General Public License v3 or later (LGPLv3+)
Classifier: Programming Language :: Python :: 3.4
Classifier: Topic :: Scientific/Engineering
Requires-Dist: numpy (>=1.14)
Requires-Dist: matplotlib (>=2.0.0)
Requires-Dist: scipy (>=1.1.0)
Requires-Dist: sympy (>=1.1.1)
Requires-Dist: brewer2mpl
Requires-Dist: testfixtures
Requires-Dist: pandas
Requires-Dist: numpydoc
Requires-Dist: IPython
Requires-Dist: sphinx (>=1.7.4)
Requires-Dist: mock
